BlackHatYitiZhaiyaoFanyi/README.md
BlackHatYitiZhaiyaoFanyi/__init__.py
BlackHatYitiZhaiyaoFanyi/__main__.py
BlackHatYitiZhaiyaoFanyi/file.epub
BlackHatYitiZhaiyaoFanyi/index.html
BlackHatYitiZhaiyaoFanyi/css/__init__.py
BlackHatYitiZhaiyaoFanyi/css/annotations.css
BlackHatYitiZhaiyaoFanyi/css/main.css
BlackHatYitiZhaiyaoFanyi/css/normalize.css
BlackHatYitiZhaiyaoFanyi/css/popup.css
BlackHatYitiZhaiyaoFanyi/font/__init__.py
BlackHatYitiZhaiyaoFanyi/font/fontello.eot
BlackHatYitiZhaiyaoFanyi/font/fontello.svg
BlackHatYitiZhaiyaoFanyi/font/fontello.ttf
BlackHatYitiZhaiyaoFanyi/font/fontello.woff
BlackHatYitiZhaiyaoFanyi/img/__init__.py
BlackHatYitiZhaiyaoFanyi/img/annotator-glyph-sprite.png
BlackHatYitiZhaiyaoFanyi/img/annotator-icon-sprite.png
BlackHatYitiZhaiyaoFanyi/img/apple-touch-icon.png
BlackHatYitiZhaiyaoFanyi/img/cancelfullscreen.png
BlackHatYitiZhaiyaoFanyi/img/close.png
BlackHatYitiZhaiyaoFanyi/img/fullscreen.png
BlackHatYitiZhaiyaoFanyi/img/loader.gif
BlackHatYitiZhaiyaoFanyi/img/menu-icon.png
BlackHatYitiZhaiyaoFanyi/img/save.png
BlackHatYitiZhaiyaoFanyi/img/saved.png
BlackHatYitiZhaiyaoFanyi/img/settings-s.png
BlackHatYitiZhaiyaoFanyi/img/settings.png
BlackHatYitiZhaiyaoFanyi/img/star.png
BlackHatYitiZhaiyaoFanyi/js/__init__.py
BlackHatYitiZhaiyaoFanyi/js/epub.js
BlackHatYitiZhaiyaoFanyi/js/epub.min.js
BlackHatYitiZhaiyaoFanyi/js/epub.min.map
BlackHatYitiZhaiyaoFanyi/js/hooks.min.js
BlackHatYitiZhaiyaoFanyi/js/hooks.min.map
BlackHatYitiZhaiyaoFanyi/js/reader.js
BlackHatYitiZhaiyaoFanyi/js/reader.js.map
BlackHatYitiZhaiyaoFanyi/js/reader.min.js
BlackHatYitiZhaiyaoFanyi/js/reader.min.map
BlackHatYitiZhaiyaoFanyi/js/hooks/__init__.py
BlackHatYitiZhaiyaoFanyi/js/hooks/extensions/__init__.py
BlackHatYitiZhaiyaoFanyi/js/hooks/extensions/highlight.js
BlackHatYitiZhaiyaoFanyi/js/libs/__init__.py
BlackHatYitiZhaiyaoFanyi/js/libs/jquery.min.js
BlackHatYitiZhaiyaoFanyi/js/libs/localforage.min.js
BlackHatYitiZhaiyaoFanyi/js/libs/screenfull.js
black_hat_yiti_zhaiyao_fanyi-2024.3.2.0.dist-info/METADATA
black_hat_yiti_zhaiyao_fanyi-2024.3.2.0.dist-info/WHEEL
black_hat_yiti_zhaiyao_fanyi-2024.3.2.0.dist-info/entry_points.txt
black_hat_yiti_zhaiyao_fanyi-2024.3.2.0.dist-info/top_level.txt
black_hat_yiti_zhaiyao_fanyi-2024.3.2.0.dist-info/RECORD
